infiniguard_health/__init__.py
infiniguard_health/infiniguard_sysconfig.py
infiniguard_health/system_state_read_write.py
infiniguard_health/utils.py
infiniguard_health/blueprints/__init__.py
infiniguard_health/blueprints/components.py
infiniguard_health/blueprints/custom_types.py
infiniguard_health/blueprints/component_blueprints/__init__.py
infiniguard_health/blueprints/component_blueprints/ddes_blueprints.py
infiniguard_health/blueprints/component_blueprints/dimms_blueprints.py
infiniguard_health/blueprints/component_blueprints/dynamic_blueprints.py
infiniguard_health/blueprints/component_blueprints/dynamic_blueprints_functions.py
infiniguard_health/blueprints/component_blueprints/eth_blueprints.py
infiniguard_health/blueprints/component_blueprints/fans_blueprints.py
infiniguard_health/blueprints/component_blueprints/fc_blueprints.py
infiniguard_health/blueprints/component_blueprints/idracs_blueprints.py
infiniguard_health/blueprints/component_blueprints/policies_blueprints.py
infiniguard_health/blueprints/component_blueprints/psus_blueprints.py
infiniguard_health/blueprints/component_blueprints/services_blueprints.py
infiniguard_health/blueprints/component_blueprints/temps_blueprints.py
infiniguard_health/blueprints/component_blueprints/volumes_blueprints.py
infiniguard_health/cli_tools/__init__.py
infiniguard_health/cli_tools/cli_tool.py
infiniguard_health/cli_tools/config.py
infiniguard_health/cli_tools/error_message_generators.py
infiniguard_health/cli_tools/health_checks.py
infiniguard_health/cli_tools/json_printer.py
infiniguard_health/data_collection/__init__.py
infiniguard_health/data_collection/collectors.py
infiniguard_health/data_collection/load_configs.py
infiniguard_health/data_collection/loaders.py
infiniguard_health/data_collection/parsers.py
infiniguard_health/data_collection/pre_load_parsers.py
infiniguard_health/data_collection/sources.py
infiniguard_health/event_engine/__init__.py
infiniguard_health/event_engine/event_engine_infra.py
infiniguard_health-1.6.3.dist-info/METADATA
infiniguard_health-1.6.3.dist-info/WHEEL
infiniguard_health-1.6.3.dist-info/entry_points.txt
infiniguard_health-1.6.3.dist-info/namespace_packages.txt
infiniguard_health-1.6.3.dist-info/top_level.txt
infiniguard_health-1.6.3.dist-info/RECORD
