Metadata-Version: 2.1
Name: infiniguard-health
Version: 1.6.3
Summary: infiniguard-health
Home-page: UNKNOWN
Author: Maxim Kigel
Author-email: mkigel@infinidat.com
License: BSD
Platform: UNKNOWN
Classifier: Intended Audience :: Developers
Classifier: Intended Audience :: System Administrators
Classifier: License :: OSI Approved :: BSD License
Classifier: Operating System :: OS Independent
Classifier: Programming Language :: Python
Classifier: Topic :: Software Development :: Libraries :: Python Modules
Requires-Dist: arrow
Requires-Dist: arrow (>=0.15.7)
Requires-Dist: bs4
Requires-Dist: capacity (>=1.3.14)
Requires-Dist: dmidecode
Requires-Dist: freezegun
Requires-Dist: iba-install (>=2.6.7)
Requires-Dist: infi.caching (>=0.0.2)
Requires-Dist: infi.storagemodel (>=0.4.33)
Requires-Dist: infinisdk
Requires-Dist: ipython
Requires-Dist: lxml
Requires-Dist: munch (>=2.5.0)
Requires-Dist: netifaces (>=0.10.9)
Requires-Dist: ntplib
Requires-Dist: parameterized (>=0.7.4)
Requires-Dist: psutil
Requires-Dist: pygments
Requires-Dist: represent (>=1.6.0)
Requires-Dist: retrying
Requires-Dist: schematics (==1.1.0.1)
Requires-Dist: setuptools
Requires-Dist: structlog
Requires-Dist: tenacity (>=6.2.0)
Requires-Dist: wrapt
Requires-Dist: xmltodict (>=0.12.0)
